{
   "current-user": {
      "name": "Bradley Ortiz",
      "username": "@bradley",
      "profile": "/assets/Profile-Photo.png",
      "tweets": [
         {
            "author": "Bradley Ortiz",
            "nickname": "@bradley",
            "time": "7m",
            "avatar": "/assets/Profile-Photo.png",
            "text": "The beautiful lake from the eastern region of Democratic Republic of Congo are very exciting... for instance the Kivu lake.",
            "image": "https://source.unsplash.com/random/800x600",
            "reply": 57,
            "retweet": 144,
            "react": 184
         },
         {
            "author": "Bradley Ortiz",
            "nickname": "@bradley",
            "time": "7m",
            "avatar": "/assets/Profile-Photo.png",
            "text": "The beautiful lake from the eastern region of Democratic Republic of Congo are very exciting... for instance the Kivu lake.",
            "image": "https://source.unsplash.com/random/800x600",
            "reply": 57,
            "retweet": 144,
            "react": 184
         }
      ]
   },
   "media": [
      {
         "author": "CNN",
         "nickname": "@CNN",
         "time": "7m",
         "avatar": "/assets/cnn.png",
         "text": "President Joe Biden touted a new agreement reached with the European Union to ease Trump-era tariffs on aluminum and steel as a 'major breakthrough' that would serve to both strengthen the US steel industry and combat the global climate crisis.",
         "image": null,
         "reply": 57,
         "retweet": 144,
         "react": 184
      },
      {
         "author": "The New York Times",
         "nickname": "@nytimes",
         "time": "2h",
         "avatar": "/assets/times.png",
         "text": "Gardening boomed during the pandemic. Six Black writers share how it has helped them re-establish, and reimagine, a connection to cultivation and the land.",
         "image": "/assets/img-post.png",
         "reply": 19,
         "retweet": 48,
         "react": 482
      },
      {
         "author": "Twitter",
         "nickname": "@twitter",
         "time": "Oct 29",
         "avatar": "/assets/twitter-logo.png",
         "text": "BIG NEWS lol jk still Twitter",
         "image": null,
         "reply": "6.8k",
         "retweet": "36.6k",
         "react": "267.1k"
      },
      {
         "author": "Twitter",
         "nickname": "@twitter",
         "time": "Oct 4",
         "avatar": "/assets/twitter-logo.png",
         "text": "hello literally everyone",
         "image": "https://source.unsplash.com/random/800x600",
         "reply": "118.7k",
         "retweet": "785.4k",
         "react": "3.3M"
      },
      {
         "author": "Twitter",
         "nickname": "Twitter",
         "time": "Oct 4",
         "avatar": "/assets/twitter-logo.png",
         "text": "hello literally everyone",
         "image": "/assets/img-post.png",
         "reply": "118.7k",
         "retweet": "785.4k",
         "react": "3.3M"
      }
   ]
}